wetest/gautomator3/__init__.py
wetest/gautomator3/__main__.py
wetest/gautomator3/const.py
wetest/gautomator3/element.py
wetest/gautomator3/gautomator.py
wetest/gautomator3/utils.py
wetest/gautomator3/core/_event.py
wetest/gautomator3/core/_exceptions.py
wetest/gautomator3/core/_reflection.py
wetest/gautomator3/core/_socket.py
wetest/gautomator3/core/_types.py
wetest_gautomator3-2.1.5.dist-info/METADATA
wetest_gautomator3-2.1.5.dist-info/WHEEL
wetest_gautomator3-2.1.5.dist-info/top_level.txt
wetest_gautomator3-2.1.5.dist-info/RECORD
