Metadata-Version: 2.1
Name: wetest-gautomator3
Version: 2.1.5
Author: Tencent WeTest
Author-email: WeTest@wetest.net
Requires-Python: >=3.6
Requires-Dist: lxml>=4.6.1
Requires-Dist: tidevice
Requires-Dist: adbutils
Requires-Dist: numpy
